easqlite/__init__.py
easqlite/_blob.py
easqlite/_connection.py
easqlite/_cursor.py
easqlite/_global.py
easqlite/_types.py
easqlite/_util.py
easqlite/py.typed
easqlite-1.1.0.dist-info/LICENSE
easqlite-1.1.0.dist-info/WHEEL
easqlite-1.1.0.dist-info/METADATA
easqlite-1.1.0.dist-info/RECORD
