Metadata-Version: 2.1
Name: easqlite
Version: 1.1.0
Summary: An executor-based async sqlite wrapper
Keywords: asyncio,sqlite
Author-email: "Taylor C. Richberger" <tcr@absolute-performance.com>
Requires-Python: >=3.8
Classifier: Development Status :: 5 - Production/Stable
Classifier: Framework :: AsyncIO
Classifier: Intended Audience :: Developers
Classifier: License :: OSI Approved :: MIT License
Classifier: Topic :: Software Development :: Libraries
Classifier: Topic :: Database :: Database Engines/Servers
Project-URL: repository, https://github.com/absperf/easqlite
